CONTRIBUTING.rst
LICENSE
MANIFEST.in
README.rst
pyproject.toml
requirements.txt
requirements_dev.txt
setup.py
pysteps/__init__.py
pysteps/datasets.py
pysteps/decorators.py
pysteps/exceptions.py
pysteps/pystepsrc
pysteps/pystepsrc_schema.json
pysteps.egg-info/PKG-INFO
pysteps.egg-info/SOURCES.txt
pysteps.egg-info/dependency_links.txt
pysteps.egg-info/requires.txt
pysteps.egg-info/top_level.txt
pysteps/blending/__init__.py
pysteps/blending/clim.py
pysteps/blending/ens_kalman_filter_methods.py
pysteps/blending/interface.py
pysteps/blending/linear_blending.py
pysteps/blending/pca_ens_kalman_filter.py
pysteps/blending/skill_scores.py
pysteps/blending/steps.py
pysteps/blending/utils.py
pysteps/cascade/__init__.py
pysteps/cascade/bandpass_filters.py
pysteps/cascade/decomposition.py
pysteps/cascade/interface.py
pysteps/downscaling/__init__.py
pysteps/downscaling/interface.py
pysteps/downscaling/rainfarm.py
pysteps/extrapolation/__init__.py
pysteps/extrapolation/interface.py
pysteps/extrapolation/semilagrangian.py
pysteps/feature/__init__.py
pysteps/feature/blob.py
pysteps/feature/interface.py
pysteps/feature/shitomasi.py
pysteps/feature/tstorm.py
pysteps/io/__init__.py
pysteps/io/archive.py
pysteps/io/exporters.py
pysteps/io/importers.py
pysteps/io/interface.py
pysteps/io/mch_lut_8bit_Metranet_AZC_V104.txt
pysteps/io/mch_lut_8bit_Metranet_v103.txt
pysteps/io/nowcast_importers.py
pysteps/io/readers.py
pysteps/motion/__init__.py
pysteps/motion/_proesmans.c
pysteps/motion/_proesmans.pyx
pysteps/motion/_vet.c
pysteps/motion/_vet.pyx
pysteps/motion/constant.py
pysteps/motion/darts.py
pysteps/motion/interface.py
pysteps/motion/lucaskanade.py
pysteps/motion/proesmans.py
pysteps/motion/vet.py
pysteps/noise/__init__.py
pysteps/noise/fftgenerators.py
pysteps/noise/interface.py
pysteps/noise/motion.py
pysteps/noise/utils.py
pysteps/nowcasts/__init__.py
pysteps/nowcasts/anvil.py
pysteps/nowcasts/extrapolation.py
pysteps/nowcasts/interface.py
pysteps/nowcasts/lagrangian_probability.py
pysteps/nowcasts/linda.py
pysteps/nowcasts/sprog.py
pysteps/nowcasts/sseps.py
pysteps/nowcasts/steps.py
pysteps/nowcasts/utils.py
