Metadata-Version: 2.4
Name: pysteps
Version: 1.19.1
Summary: Python framework for short-term ensemble prediction systems
Home-page: https://pysteps.github.io/
Author: PySteps developers
License: LICENSE
Project-URL: Source, https://github.com/pySTEPS/pysteps
Project-URL: Issues, https://github.com/pySTEPS/pysteps/issues
Project-URL: CI, https://github.com/pySTEPS/pysteps/actions
Project-URL: Changelog, https://github.com/pySTEPS/pysteps/releases
Project-URL: Documentation, https://pysteps.readthedocs.io
Classifier: Development Status :: 5 - Production/Stable
Classifier: Intended Audience :: Science/Research
Classifier: Topic :: Scientific/Engineering
Classifier: Topic :: Scientific/Engineering :: Atmospheric Science
Classifier: Topic :: Scientific/Engineering :: Hydrology
Classifier: License :: OSI Approved :: BSD License
Classifier: Programming Language :: Python :: 3 :: Only
Classifier: Programming Language :: Python :: 3.11
Classifier: Programming Language :: Python :: 3.12
Classifier: Programming Language :: Python :: 3.13
Classifier: Operating System :: OS Independent
License-File: LICENSE
Requires-Dist: numpy
Requires-Dist: jsmin
Requires-Dist: scipy
Requires-Dist: matplotlib
Requires-Dist: jsonschema
Dynamic: author
Dynamic: classifier
Dynamic: description
Dynamic: description-content-type
Dynamic: home-page
Dynamic: license
Dynamic: license-file
Dynamic: project-url
Dynamic: requires-dist
Dynamic: summary
